hawthorn/__init__.py
hawthorn/amqplib.py
hawthorn/asynchttphandler.py
hawthorn/asyncrequest.py
hawthorn/behaviors.py
hawthorn/cacheproxy.py
hawthorn/db2cachehelper.py
hawthorn/dbproxy.py
hawthorn/elasticsearchsaver.py
hawthorn/exceptionreporter.py
hawthorn/guniapp.py
hawthorn/migrationutils.py
hawthorn/modelutils.py
hawthorn/registerroute.py
hawthorn/session.py
hawthorn/singleton.py
hawthorn/supports.py
hawthorn/webapplication.py
hawthorn/cacher/__init__.py
hawthorn/cacher/filecache.py
hawthorn/formvalidation/__init__.py
hawthorn/formvalidation/formutils.py
hawthorn/locales/basic.en_US.yaml
hawthorn/locales/basic.en_US.yml
hawthorn/locales/basic.zh_CN.yaml
hawthorn/locales/basic.zh_CN.yml
hawthorn/modelutils/__init__.py
hawthorn/modelutils/behaviors.py
hawthorn/modelutils/supports/__init__.py
hawthorn/modelutils/supports/migration.py
hawthorn/modelutils/supports/migration_progress.py
hawthorn/restfulwrapper/__init__.py
hawthorn/restfulwrapper/definations.py
hawthorn/restfulwrapper/modelapihandlers.py
hawthorn/restfulwrapper/modeldescriptorhandlers.py
hawthorn/restfulwrapper/pagedescriptorhandlers.py
hawthorn/restfulwrapper/register.py
hawthorn/restfulwrapper/relationmodelapihandlers.py
hawthorn/restfulwrapper/utils.py
hawthorn/restfulwrapper/accesscontrol/__init__.py
hawthorn/restfulwrapper/accesscontrol/authorizedsession.py
hawthorn/sqlalchemy_dialects/__init__.py
hawthorn/sqlalchemy_dialects/asyncpg_migrate/__init__.py
hawthorn/sqlalchemy_dialects/sync_threading/__init__.py
hawthorn/sqlalchemy_dialects/sync_threading/asyncio.py
hawthorn/sqlalchemy_dialects/sync_threading/base.py
hawthorn/sqlalchemy_dialects/sync_threading/exc.py
hawthorn/tornadoadapts/__init__.py
hawthorn/tornadoadapts/stack_context.py
hawthorn/tornadozeep/__init__.py
hawthorn/tornadozeep/bindings.py
hawthorn/tornadozeep/transport.py
hawthorn/utilities/__init__.py
hawthorn/utilities/aescoder.py
hawthorn/utilities/descoder.py
hawthorn/utilities/fileutil.py
hawthorn/utilities/htmldocutils.py
hawthorn-0.0.6.dist-info/LICENSE
hawthorn-0.0.6.dist-info/METADATA
hawthorn-0.0.6.dist-info/WHEEL
hawthorn-0.0.6.dist-info/top_level.txt
hawthorn-0.0.6.dist-info/RECORD
